ms_graph/client.py
ms_graph/drive_items.py
ms_graph/drives.py
ms_graph/groups.py
ms_graph/mail.py
ms_graph/notes.py
ms_graph/personal_contacts.py
ms_graph/search.py
ms_graph/session.py
ms_graph/users.py
ms_graph/utils/range.py
ms_graph/workbooks_and_charts/application.py
ms_graph/workbooks_and_charts/comments.py
ms_graph/workbooks_and_charts/enums.py
ms_graph/workbooks_and_charts/range.py
ms_graph/workbooks_and_charts/workbook.py
ms_graph/workbooks_and_charts/worksheets.py
ms_graph_python_client-0.1.0.dist-info/LICENSE
ms_graph_python_client-0.1.0.dist-info/METADATA
ms_graph_python_client-0.1.0.dist-info/WHEEL
ms_graph_python_client-0.1.0.dist-info/top_level.txt
ms_graph_python_client-0.1.0.dist-info/RECORD
