Metadata-Version: 2.1
Name: ms-graph-python-client
Version: 0.1.0
Summary: A Python Client Application that allows interaction with the Microsoft Graph API.
Home-page: https://github.com/areed1192/ms-graph-python-client
Author: Alex Reed
Author-email: coding.sigma@gmail.com
License: UNKNOWN
Platform: UNKNOWN
Requires-Python: >3.8
License-File: LICENSE
Requires-Dist: requests
Requires-Dist: msal
